{"nodes": [{"id": "c_users_pc_projects_projects_jepangku_jepangku_news_docs_feature_status_md", "label": "feature-status.md", "file_type": "document", "source_file": "docs/feature-status.md", "source_location": "L1"}, {"id": "docs_feature_status_status_fitur_checklist_jepangku_news", "label": "Status Fitur & Checklist \u2014 Jepangku News", "file_type": "document", "source_file": "docs/feature-status.md", "source_location": "L1"}, {"id": "docs_feature_status_daftar_isi", "label": "Daftar isi", "file_type": "document", "source_file": "docs/feature-status.md", "source_location": "L12"}, {"id": "docs_feature_status_ringkasan", "label": "Ringkasan", "file_type": "document", "source_file": "docs/feature-status.md", "source_location": "L22"}, {"id": "docs_feature_status_sudah_diimplementasi_per_domain_1_20", "label": "Sudah Diimplementasi \u2014 per domain \u00a71\u2013\u00a720", "file_type": "document", "source_file": "docs/feature-status.md", "source_location": "L33"}, {"id": "docs_feature_status_1_autentikasi_akun", "label": "\u00a71 Autentikasi & akun", "file_type": "document", "source_file": "docs/feature-status.md", "source_location": "L35"}, {"id": "docs_feature_status_2_profil_data_user", "label": "\u00a72 Profil & data user", "file_type": "document", "source_file": "docs/feature-status.md", "source_location": "L57"}, {"id": "docs_feature_status_3_artikel", "label": "\u00a73 Artikel", "file_type": "document", "source_file": "docs/feature-status.md", "source_location": "L65"}, {"id": "docs_feature_status_4_kuis", "label": "\u00a74 Kuis", "file_type": "document", "source_file": "docs/feature-status.md", "source_location": "L79"}, {"id": "docs_feature_status_5_poll", "label": "\u00a75 Poll", "file_type": "document", "source_file": "docs/feature-status.md", "source_location": "L87"}, {"id": "docs_feature_status_6_video_jepangku_tv", "label": "\u00a76 Video \u2014 Jepangku TV", "file_type": "document", "source_file": "docs/feature-status.md", "source_location": "L94"}, {"id": "docs_feature_status_7_engagement_interaksi", "label": "\u00a77 Engagement & interaksi", "file_type": "document", "source_file": "docs/feature-status.md", "source_location": "L103"}, {"id": "docs_feature_status_8_gamifikasi_poin_leaderboard", "label": "\u00a78 Gamifikasi \u2014 poin & leaderboard", "file_type": "document", "source_file": "docs/feature-status.md", "source_location": "L113"}, {"id": "docs_feature_status_9_notifikasi_email", "label": "\u00a79 Notifikasi & email", "file_type": "document", "source_file": "docs/feature-status.md", "source_location": "L127"}, {"id": "docs_feature_status_10_newsletter", "label": "\u00a710 Newsletter", "file_type": "document", "source_file": "docs/feature-status.md", "source_location": "L140"}, {"id": "docs_feature_status_11_kontributor", "label": "\u00a711 Kontributor", "file_type": "document", "source_file": "docs/feature-status.md", "source_location": "L148"}, {"id": "docs_feature_status_12_homepage_discovery", "label": "\u00a712 Homepage & discovery", "file_type": "document", "source_file": "docs/feature-status.md", "source_location": "L158"}, {"id": "docs_feature_status_13_integrasi_lms_teaser", "label": "\u00a713 Integrasi LMS teaser", "file_type": "document", "source_file": "docs/feature-status.md", "source_location": "L170"}, {"id": "docs_feature_status_14_iklan_monetisasi", "label": "\u00a714 Iklan & monetisasi", "file_type": "document", "source_file": "docs/feature-status.md", "source_location": "L177"}, {"id": "docs_feature_status_15_admin_dashboard_monitoring", "label": "\u00a715 Admin \u2014 dashboard & monitoring", "file_type": "document", "source_file": "docs/feature-status.md", "source_location": "L183"}, {"id": "docs_feature_status_16_admin_konten_taxonomi", "label": "\u00a716 Admin \u2014 konten & taxonomi", "file_type": "document", "source_file": "docs/feature-status.md", "source_location": "L191"}, {"id": "docs_feature_status_17_admin_analytics", "label": "\u00a717 Admin \u2014 analytics", "file_type": "document", "source_file": "docs/feature-status.md", "source_location": "L197"}, {"id": "docs_feature_status_18_halaman_statis_navigasi", "label": "\u00a718 Halaman statis & navigasi", "file_type": "document", "source_file": "docs/feature-status.md", "source_location": "L203"}, {"id": "docs_feature_status_19_upload_media", "label": "\u00a719 Upload & media", "file_type": "document", "source_file": "docs/feature-status.md", "source_location": "L218"}, {"id": "docs_feature_status_20_non_functional_qa", "label": "\u00a720 Non-functional & QA", "file_type": "document", "source_file": "docs/feature-status.md", "source_location": "L224"}, {"id": "docs_feature_status_infrastruktur_revisi_ui_lintas_domain", "label": "Infrastruktur & revisi UI *(lintas domain)*", "file_type": "document", "source_file": "docs/feature-status.md", "source_location": "L236"}, {"id": "docs_feature_status_soft_launch_konten_operasional_editorial", "label": "Soft launch konten *(operasional editorial)*", "file_type": "document", "source_file": "docs/feature-status.md", "source_location": "L242"}, {"id": "docs_feature_status_todo_dari_kode_tier_a_f_audit_juni_2026_selesai", "label": "TODO dari kode \u2014 Tier A\u2013F *(audit Juni 2026, selesai)*", "file_type": "document", "source_file": "docs/feature-status.md", "source_location": "L250"}, {"id": "docs_feature_status_checklist_testing_kerjakan", "label": "Checklist Testing \u2014 Kerjakan", "file_type": "document", "source_file": "docs/feature-status.md", "source_location": "L263"}, {"id": "docs_feature_status_fase_0_infrastruktur", "label": "Fase 0 \u2014 Infrastruktur", "file_type": "document", "source_file": "docs/feature-status.md", "source_location": "L268"}, {"id": "docs_feature_status_fase_1_unit_test_lib_156_kasus", "label": "Fase 1 \u2014 Unit test `lib/` *(~156 kasus)*", "file_type": "document", "source_file": "docs/feature-status.md", "source_location": "L278"}, {"id": "docs_feature_status_fase_2_api_integration_inti_7_modul", "label": "Fase 2 \u2014 API integration inti *(~7 modul)*", "file_type": "document", "source_file": "docs/feature-status.md", "source_location": "L284"}, {"id": "docs_feature_status_fase_3_qa_manual_browser_tidak_otomatis", "label": "Fase 3 \u2014 QA manual browser *(tidak otomatis)*", "file_type": "document", "source_file": "docs/feature-status.md", "source_location": "L294"}, {"id": "docs_feature_status_1_autentikasi_akun_10_fitur_19_kondisi", "label": "\u00a71 Autentikasi & akun *(10 fitur \u00b7 19 kondisi)*", "file_type": "document", "source_file": "docs/feature-status.md", "source_location": "L300"}, {"id": "docs_feature_status_2_profil_data_user_8_fitur_13_kondisi", "label": "\u00a72 Profil & data user *(8 fitur \u00b7 13 kondisi)*", "file_type": "document", "source_file": "docs/feature-status.md", "source_location": "L313"}, {"id": "docs_feature_status_3_artikel_22_fitur_28_kondisi", "label": "\u00a73 Artikel *(22 fitur \u00b7 28 kondisi)*", "file_type": "document", "source_file": "docs/feature-status.md", "source_location": "L324"}, {"id": "docs_feature_status_4_kuis_7_fitur_11_kondisi", "label": "\u00a74 Kuis *(7 fitur \u00b7 11 kondisi)*", "file_type": "document", "source_file": "docs/feature-status.md", "source_location": "L349"}, {"id": "docs_feature_status_5_poll_5_fitur_7_kondisi", "label": "\u00a75 Poll *(5 fitur \u00b7 7 kondisi)*", "file_type": "document", "source_file": "docs/feature-status.md", "source_location": "L359"}, {"id": "docs_feature_status_6_video_jepangku_tv_5_fitur_6_kondisi", "label": "\u00a76 Video \u2014 Jepangku TV *(5 fitur \u00b7 6 kondisi)*", "file_type": "document", "source_file": "docs/feature-status.md", "source_location": "L367"}, {"id": "docs_feature_status_7_engagement_interaksi_10_fitur_11_kondisi", "label": "\u00a77 Engagement & interaksi *(10 fitur \u00b7 11 kondisi)*", "file_type": "document", "source_file": "docs/feature-status.md", "source_location": "L376"}, {"id": "docs_feature_status_8_gamifikasi_poin_leaderboard_11_fitur_12_kondisi", "label": "\u00a78 Gamifikasi \u2014 poin & leaderboard *(11 fitur \u00b7 12 kondisi)*", "file_type": "document", "source_file": "docs/feature-status.md", "source_location": "L389"}, {"id": "docs_feature_status_9_notifikasi_email_15_fitur_16_kondisi", "label": "\u00a79 Notifikasi & email *(15 fitur \u00b7 16 kondisi)*", "file_type": "document", "source_file": "docs/feature-status.md", "source_location": "L403"}, {"id": "docs_feature_status_10_newsletter_6_fitur_8_kondisi", "label": "\u00a710 Newsletter *(6 fitur \u00b7 8 kondisi)*", "file_type": "document", "source_file": "docs/feature-status.md", "source_location": "L421"}, {"id": "docs_feature_status_11_kontributor_5_fitur_6_kondisi", "label": "\u00a711 Kontributor *(5 fitur \u00b7 6 kondisi)*", "file_type": "document", "source_file": "docs/feature-status.md", "source_location": "L430"}, {"id": "docs_feature_status_12_homepage_discovery_14_fitur_17_kondisi", "label": "\u00a712 Homepage & discovery *(14 fitur \u00b7 17 kondisi)*", "file_type": "document", "source_file": "docs/feature-status.md", "source_location": "L438"}, {"id": "docs_feature_status_13_integrasi_lms_teaser_6_fitur_7_kondisi", "label": "\u00a713 Integrasi LMS teaser *(6 fitur \u00b7 7 kondisi)*", "file_type": "document", "source_file": "docs/feature-status.md", "source_location": "L455"}, {"id": "docs_feature_status_14_iklan_monetisasi_4_fitur_5_kondisi", "label": "\u00a714 Iklan & monetisasi *(4 fitur \u00b7 5 kondisi)*", "file_type": "document", "source_file": "docs/feature-status.md", "source_location": "L464"}, {"id": "docs_feature_status_15_admin_dashboard_monitoring_6_fitur_9_kondisi", "label": "\u00a715 Admin \u2014 dashboard & monitoring *(6 fitur \u00b7 9 kondisi)*", "file_type": "document", "source_file": "docs/feature-status.md", "source_location": "L471"}, {"id": "docs_feature_status_16_admin_konten_taxonomi_5_fitur_5_kondisi", "label": "\u00a716 Admin \u2014 konten & taxonomi *(5 fitur \u00b7 5 kondisi)*", "file_type": "document", "source_file": "docs/feature-status.md", "source_location": "L480"}, {"id": "docs_feature_status_17_admin_analytics_5_fitur_5_kondisi", "label": "\u00a717 Admin \u2014 analytics *(5 fitur \u00b7 5 kondisi)*", "file_type": "document", "source_file": "docs/feature-status.md", "source_location": "L488"}, {"id": "docs_feature_status_18_halaman_statis_navigasi_12_fitur_14_kondisi", "label": "\u00a718 Halaman statis & navigasi *(12 fitur \u00b7 14 kondisi)*", "file_type": "document", "source_file": "docs/feature-status.md", "source_location": "L496"}, {"id": "docs_feature_status_19_upload_media_4_fitur_4_kondisi", "label": "\u00a719 Upload & media *(4 fitur \u00b7 4 kondisi)*", "file_type": "document", "source_file": "docs/feature-status.md", "source_location": "L506"}, {"id": "docs_feature_status_20_non_functional_29_kondisi", "label": "\u00a720 Non-functional *(29 kondisi)*", "file_type": "document", "source_file": "docs/feature-status.md", "source_location": "L513"}, {"id": "docs_feature_status_rencana_lanjutan_bisa_nanti_ekosistem_fase_d_e", "label": "Rencana Lanjutan \u2014 Bisa Nanti *(ekosistem Fase D/E)*", "file_type": "document", "source_file": "docs/feature-status.md", "source_location": "L547"}, {"id": "docs_feature_status_referensi", "label": "Referensi", "file_type": "document", "source_file": "docs/feature-status.md", "source_location": "L559"}], "edges": [{"source": "c_users_pc_projects_projects_jepangku_jepangku_news_docs_feature_status_md", "target": "docs_feature_status_status_fitur_checklist_jepangku_news", "relation": "contains", "confidence": "EXTRACTED", "source_file": "docs/feature-status.md", "source_location": "L1", "weight": 1.0}, {"source": "docs_feature_status_status_fitur_checklist_jepangku_news", "target": "docs_feature_status_daftar_isi", "relation": "contains", "confidence": "EXTRACTED", "source_file": "docs/feature-status.md", "source_location": "L12", "weight": 1.0}, {"source": "docs_feature_status_status_fitur_checklist_jepangku_news", "target": "docs_feature_status_ringkasan", "relation": "contains", "confidence": "EXTRACTED", "source_file": "docs/feature-status.md", "source_location": "L22", "weight": 1.0}, {"source": "docs_feature_status_status_fitur_checklist_jepangku_news", "target": "docs_feature_status_sudah_diimplementasi_per_domain_1_20", "relation": "contains", "confidence": "EXTRACTED", "source_file": "docs/feature-status.md", "source_location": "L33", "weight": 1.0}, {"source": "docs_feature_status_sudah_diimplementasi_per_domain_1_20", "target": "docs_feature_status_1_autentikasi_akun", "relation": "contains", "confidence": "EXTRACTED", "source_file": "docs/feature-status.md", "source_location": "L35", "weight": 1.0}, {"source": "docs_feature_status_sudah_diimplementasi_per_domain_1_20", "target": "docs_feature_status_2_profil_data_user", "relation": "contains", "confidence": "EXTRACTED", "source_file": "docs/feature-status.md", "source_location": "L57", "weight": 1.0}, {"source": "docs_feature_status_sudah_diimplementasi_per_domain_1_20", "target": "docs_feature_status_3_artikel", "relation": "contains", "confidence": "EXTRACTED", "source_file": "docs/feature-status.md", "source_location": "L65", "weight": 1.0}, {"source": "docs_feature_status_sudah_diimplementasi_per_domain_1_20", "target": "docs_feature_status_4_kuis", "relation": "contains", "confidence": "EXTRACTED", "source_file": "docs/feature-status.md", "source_location": "L79", "weight": 1.0}, {"source": "docs_feature_status_sudah_diimplementasi_per_domain_1_20", "target": "docs_feature_status_5_poll", "relation": "contains", "confidence": "EXTRACTED", "source_file": "docs/feature-status.md", "source_location": "L87", "weight": 1.0}, {"source": "docs_feature_status_sudah_diimplementasi_per_domain_1_20", "target": "docs_feature_status_6_video_jepangku_tv", "relation": "contains", "confidence": "EXTRACTED", "source_file": "docs/feature-status.md", "source_location": "L94", "weight": 1.0}, {"source": "docs_feature_status_sudah_diimplementasi_per_domain_1_20", "target": "docs_feature_status_7_engagement_interaksi", "relation": "contains", "confidence": "EXTRACTED", "source_file": "docs/feature-status.md", "source_location": "L103", "weight": 1.0}, {"source": "docs_feature_status_sudah_diimplementasi_per_domain_1_20", "target": "docs_feature_status_8_gamifikasi_poin_leaderboard", "relation": "contains", "confidence": "EXTRACTED", "source_file": "docs/feature-status.md", "source_location": "L113", "weight": 1.0}, {"source": "docs_feature_status_sudah_diimplementasi_per_domain_1_20", "target": "docs_feature_status_9_notifikasi_email", "relation": "contains", "confidence": "EXTRACTED", "source_file": "docs/feature-status.md", "source_location": "L127", "weight": 1.0}, {"source": "docs_feature_status_sudah_diimplementasi_per_domain_1_20", "target": "docs_feature_status_10_newsletter", "relation": "contains", "confidence": "EXTRACTED", "source_file": "docs/feature-status.md", "source_location": "L140", "weight": 1.0}, {"source": "docs_feature_status_sudah_diimplementasi_per_domain_1_20", "target": "docs_feature_status_11_kontributor", "relation": "contains", "confidence": "EXTRACTED", "source_file": "docs/feature-status.md", "source_location": "L148", "weight": 1.0}, {"source": "docs_feature_status_sudah_diimplementasi_per_domain_1_20", "target": "docs_feature_status_12_homepage_discovery", "relation": "contains", "confidence": "EXTRACTED", "source_file": "docs/feature-status.md", "source_location": "L158", "weight": 1.0}, {"source": "docs_feature_status_sudah_diimplementasi_per_domain_1_20", "target": "docs_feature_status_13_integrasi_lms_teaser", "relation": "contains", "confidence": "EXTRACTED", "source_file": "docs/feature-status.md", "source_location": "L170", "weight": 1.0}, {"source": "docs_feature_status_sudah_diimplementasi_per_domain_1_20", "target": "docs_feature_status_14_iklan_monetisasi", "relation": "contains", "confidence": "EXTRACTED", "source_file": "docs/feature-status.md", "source_location": "L177", "weight": 1.0}, {"source": "docs_feature_status_sudah_diimplementasi_per_domain_1_20", "target": "docs_feature_status_15_admin_dashboard_monitoring", "relation": "contains", "confidence": "EXTRACTED", "source_file": "docs/feature-status.md", "source_location": "L183", "weight": 1.0}, {"source": "docs_feature_status_sudah_diimplementasi_per_domain_1_20", "target": "docs_feature_status_16_admin_konten_taxonomi", "relation": "contains", "confidence": "EXTRACTED", "source_file": "docs/feature-status.md", "source_location": "L191", "weight": 1.0}, {"source": "docs_feature_status_sudah_diimplementasi_per_domain_1_20", "target": "docs_feature_status_17_admin_analytics", "relation": "contains", "confidence": "EXTRACTED", "source_file": "docs/feature-status.md", "source_location": "L197", "weight": 1.0}, {"source": "docs_feature_status_sudah_diimplementasi_per_domain_1_20", "target": "docs_feature_status_18_halaman_statis_navigasi", "relation": "contains", "confidence": "EXTRACTED", "source_file": "docs/feature-status.md", "source_location": "L203", "weight": 1.0}, {"source": "docs_feature_status_sudah_diimplementasi_per_domain_1_20", "target": "docs_feature_status_19_upload_media", "relation": "contains", "confidence": "EXTRACTED", "source_file": "docs/feature-status.md", "source_location": "L218", "weight": 1.0}, {"source": "docs_feature_status_sudah_diimplementasi_per_domain_1_20", "target": "docs_feature_status_20_non_functional_qa", "relation": "contains", "confidence": "EXTRACTED", "source_file": "docs/feature-status.md", "source_location": "L224", "weight": 1.0}, {"source": "docs_feature_status_sudah_diimplementasi_per_domain_1_20", "target": "docs_feature_status_infrastruktur_revisi_ui_lintas_domain", "relation": "contains", "confidence": "EXTRACTED", "source_file": "docs/feature-status.md", "source_location": "L236", "weight": 1.0}, {"source": "docs_feature_status_sudah_diimplementasi_per_domain_1_20", "target": "docs_feature_status_soft_launch_konten_operasional_editorial", "relation": "contains", "confidence": "EXTRACTED", "source_file": "docs/feature-status.md", "source_location": "L242", "weight": 1.0}, {"source": "docs_feature_status_sudah_diimplementasi_per_domain_1_20", "target": "docs_feature_status_todo_dari_kode_tier_a_f_audit_juni_2026_selesai", "relation": "contains", "confidence": "EXTRACTED", "source_file": "docs/feature-status.md", "source_location": "L250", "weight": 1.0}, {"source": "docs_feature_status_status_fitur_checklist_jepangku_news", "target": "docs_feature_status_checklist_testing_kerjakan", "relation": "contains", "confidence": "EXTRACTED", "source_file": "docs/feature-status.md", "source_location": "L263", "weight": 1.0}, {"source": "docs_feature_status_checklist_testing_kerjakan", "target": "docs_feature_status_fase_0_infrastruktur", "relation": "contains", "confidence": "EXTRACTED", "source_file": "docs/feature-status.md", "source_location": "L268", "weight": 1.0}, {"source": "docs_feature_status_checklist_testing_kerjakan", "target": "docs_feature_status_fase_1_unit_test_lib_156_kasus", "relation": "contains", "confidence": "EXTRACTED", "source_file": "docs/feature-status.md", "source_location": "L278", "weight": 1.0}, {"source": "docs_feature_status_checklist_testing_kerjakan", "target": "docs_feature_status_fase_2_api_integration_inti_7_modul", "relation": "contains", "confidence": "EXTRACTED", "source_file": "docs/feature-status.md", "source_location": "L284", "weight": 1.0}, {"source": "docs_feature_status_checklist_testing_kerjakan", "target": "docs_feature_status_fase_3_qa_manual_browser_tidak_otomatis", "relation": "contains", "confidence": "EXTRACTED", "source_file": "docs/feature-status.md", "source_location": "L294", "weight": 1.0}, {"source": "docs_feature_status_checklist_testing_kerjakan", "target": "docs_feature_status_1_autentikasi_akun_10_fitur_19_kondisi", "relation": "contains", "confidence": "EXTRACTED", "source_file": "docs/feature-status.md", "source_location": "L300", "weight": 1.0}, {"source": "docs_feature_status_checklist_testing_kerjakan", "target": "docs_feature_status_2_profil_data_user_8_fitur_13_kondisi", "relation": "contains", "confidence": "EXTRACTED", "source_file": "docs/feature-status.md", "source_location": "L313", "weight": 1.0}, {"source": "docs_feature_status_checklist_testing_kerjakan", "target": "docs_feature_status_3_artikel_22_fitur_28_kondisi", "relation": "contains", "confidence": "EXTRACTED", "source_file": "docs/feature-status.md", "source_location": "L324", "weight": 1.0}, {"source": "docs_feature_status_checklist_testing_kerjakan", "target": "docs_feature_status_4_kuis_7_fitur_11_kondisi", "relation": "contains", "confidence": "EXTRACTED", "source_file": "docs/feature-status.md", "source_location": "L349", "weight": 1.0}, {"source": "docs_feature_status_checklist_testing_kerjakan", "target": "docs_feature_status_5_poll_5_fitur_7_kondisi", "relation": "contains", "confidence": "EXTRACTED", "source_file": "docs/feature-status.md", "source_location": "L359", "weight": 1.0}, {"source": "docs_feature_status_checklist_testing_kerjakan", "target": "docs_feature_status_6_video_jepangku_tv_5_fitur_6_kondisi", "relation": "contains", "confidence": "EXTRACTED", "source_file": "docs/feature-status.md", "source_location": "L367", "weight": 1.0}, {"source": "docs_feature_status_checklist_testing_kerjakan", "target": "docs_feature_status_7_engagement_interaksi_10_fitur_11_kondisi", "relation": "contains", "confidence": "EXTRACTED", "source_file": "docs/feature-status.md", "source_location": "L376", "weight": 1.0}, {"source": "docs_feature_status_checklist_testing_kerjakan", "target": "docs_feature_status_8_gamifikasi_poin_leaderboard_11_fitur_12_kondisi", "relation": "contains", "confidence": "EXTRACTED", "source_file": "docs/feature-status.md", "source_location": "L389", "weight": 1.0}, {"source": "docs_feature_status_checklist_testing_kerjakan", "target": "docs_feature_status_9_notifikasi_email_15_fitur_16_kondisi", "relation": "contains", "confidence": "EXTRACTED", "source_file": "docs/feature-status.md", "source_location": "L403", "weight": 1.0}, {"source": "docs_feature_status_checklist_testing_kerjakan", "target": "docs_feature_status_10_newsletter_6_fitur_8_kondisi", "relation": "contains", "confidence": "EXTRACTED", "source_file": "docs/feature-status.md", "source_location": "L421", "weight": 1.0}, {"source": "docs_feature_status_checklist_testing_kerjakan", "target": "docs_feature_status_11_kontributor_5_fitur_6_kondisi", "relation": "contains", "confidence": "EXTRACTED", "source_file": "docs/feature-status.md", "source_location": "L430", "weight": 1.0}, {"source": "docs_feature_status_checklist_testing_kerjakan", "target": "docs_feature_status_12_homepage_discovery_14_fitur_17_kondisi", "relation": "contains", "confidence": "EXTRACTED", "source_file": "docs/feature-status.md", "source_location": "L438", "weight": 1.0}, {"source": "docs_feature_status_checklist_testing_kerjakan", "target": "docs_feature_status_13_integrasi_lms_teaser_6_fitur_7_kondisi", "relation": "contains", "confidence": "EXTRACTED", "source_file": "docs/feature-status.md", "source_location": "L455", "weight": 1.0}, {"source": "docs_feature_status_checklist_testing_kerjakan", "target": "docs_feature_status_14_iklan_monetisasi_4_fitur_5_kondisi", "relation": "contains", "confidence": "EXTRACTED", "source_file": "docs/feature-status.md", "source_location": "L464", "weight": 1.0}, {"source": "docs_feature_status_checklist_testing_kerjakan", "target": "docs_feature_status_15_admin_dashboard_monitoring_6_fitur_9_kondisi", "relation": "contains", "confidence": "EXTRACTED", "source_file": "docs/feature-status.md", "source_location": "L471", "weight": 1.0}, {"source": "docs_feature_status_checklist_testing_kerjakan", "target": "docs_feature_status_16_admin_konten_taxonomi_5_fitur_5_kondisi", "relation": "contains", "confidence": "EXTRACTED", "source_file": "docs/feature-status.md", "source_location": "L480", "weight": 1.0}, {"source": "docs_feature_status_checklist_testing_kerjakan", "target": "docs_feature_status_17_admin_analytics_5_fitur_5_kondisi", "relation": "contains", "confidence": "EXTRACTED", "source_file": "docs/feature-status.md", "source_location": "L488", "weight": 1.0}, {"source": "docs_feature_status_checklist_testing_kerjakan", "target": "docs_feature_status_18_halaman_statis_navigasi_12_fitur_14_kondisi", "relation": "contains", "confidence": "EXTRACTED", "source_file": "docs/feature-status.md", "source_location": "L496", "weight": 1.0}, {"source": "docs_feature_status_checklist_testing_kerjakan", "target": "docs_feature_status_19_upload_media_4_fitur_4_kondisi", "relation": "contains", "confidence": "EXTRACTED", "source_file": "docs/feature-status.md", "source_location": "L506", "weight": 1.0}, {"source": "docs_feature_status_checklist_testing_kerjakan", "target": "docs_feature_status_20_non_functional_29_kondisi", "relation": "contains", "confidence": "EXTRACTED", "source_file": "docs/feature-status.md", "source_location": "L513", "weight": 1.0}, {"source": "docs_feature_status_status_fitur_checklist_jepangku_news", "target": "docs_feature_status_rencana_lanjutan_bisa_nanti_ekosistem_fase_d_e", "relation": "contains", "confidence": "EXTRACTED", "source_file": "docs/feature-status.md", "source_location": "L547", "weight": 1.0}, {"source": "docs_feature_status_status_fitur_checklist_jepangku_news", "target": "docs_feature_status_referensi", "relation": "contains", "confidence": "EXTRACTED", "source_file": "docs/feature-status.md", "source_location": "L559", "weight": 1.0}], "input_tokens": 0, "output_tokens": 0}